opengov/__init__.py
opengov/__version__.py
opengov/cli.py
opengov/fda.py
opengov/opengov.py
opengov/utils.py
opengov-0.1.1.dist-info/AUTHORS.rst
opengov-0.1.1.dist-info/LICENSE
opengov-0.1.1.dist-info/METADATA
opengov-0.1.1.dist-info/WHEEL
opengov-0.1.1.dist-info/entry_points.txt
opengov-0.1.1.dist-info/top_level.txt
opengov-0.1.1.dist-info/RECORD
