Metadata-Version: 2.1
Name: opengov
Version: 0.1.1
Summary: Reliable up-to-date datahub for publicly available data from US government.
Home-page: https://github.com/greatcr7/opengov
Author: Brandon Jin
Author-email: brandonjincmu@gmail.com
License: MIT license
Keywords: data,Open Government
Platform: UNKNOWN
Classifier: Development Status :: 2 - Pre-Alpha
Classifier: Intended Audience :: Developers
Classifier: License :: OSI Approved :: MIT License
Classifier: Natural Language :: English
Classifier: Programming Language :: Python :: 3
Classifier: Programming Language :: Python :: 3.5
Classifier: Programming Language :: Python :: 3.6
Classifier: Programming Language :: Python :: 3.7
Classifier: Programming Language :: Python :: 3.8
Requires-Python: >=3
Requires-Dist: requests
